klio_core/__init__.py
klio_core/_testing.py
klio_core/dataflow.py
klio_core/exceptions.py
klio_core/options.py
klio_core/utils.py
klio_core/variables.py
klio_core/config/__init__.py
klio_core/config/_converters.py
klio_core/config/_io.py
klio_core/config/_preprocessing.py
klio_core/config/_utils.py
klio_core/config/core.py
klio_core/proto/__init__.py
klio_core/proto/klio.proto
klio_core/proto/klio_pb2.py
klio_core/proto/v1beta1/__init__.py
klio_core/proto/v1beta1/klio_pb2.py
klio_core-22.3.0.dist-info/METADATA
klio_core-22.3.0.dist-info/WHEEL
klio_core-22.3.0.dist-info/top_level.txt
klio_core-22.3.0.dist-info/RECORD
