Metadata-Version: 2.1
Name: klio-core
Version: 22.3.0
Summary: Core klio library for common functionality
Home-page: https://github.com/spotify/klio
Author: The klio developers
Author-email: opensource+klio@spotify.com
Maintainer: The klio developers
Maintainer-email: opensource+klio@spotify.com
License: UNKNOWN
Project-URL: Documentation, https://docs.klio.io
Project-URL: Bug Tracker, https://github.com/spotify/klio/issues
Project-URL: Source Code, https://github.com/spotify/klio
Keywords: klio,apache,beam,audio
Platform: UNKNOWN
Classifier: Development Status :: 3 - Alpha
Classifier: Natural Language :: English
Classifier: Operating System :: POSIX :: Linux
Classifier: Operating System :: MacOS :: MacOS X
Classifier: Programming Language :: Python
Classifier: Programming Language :: Python :: 3.6
Classifier: Programming Language :: Python :: 3.7
Classifier: Programming Language :: Python :: 3.8
Classifier: Programming Language :: Python :: Implementation :: CPython
Classifier: License :: OSI Approved :: Apache Software License
Classifier: Topic :: Software Development :: Libraries
Classifier: Topic :: Software Development :: Libraries :: Python Modules
Classifier: Topic :: Multimedia
Classifier: Topic :: Multimedia :: Graphics
Classifier: Topic :: Multimedia :: Sound/Audio
Classifier: Topic :: Multimedia :: Video
Classifier: Topic :: Scientific/Engineering
Classifier: Topic :: Scientific/Engineering :: Image Processing
Requires-Python: >=3.6, <3.9
Requires-Dist: click
Requires-Dist: glom
Requires-Dist: google-api-python-client
Requires-Dist: google-api-core (>=1.21.0)
Requires-Dist: google-cloud-core (>=1.4.1)
Requires-Dist: google-cloud-pubsub
Requires-Dist: protobuf (>=3.12.0)
Requires-Dist: pyyaml
Requires-Dist: six
Requires-Dist: attrs
Provides-Extra: dev
Requires-Dist: sphinx ; extra == 'dev'
Requires-Dist: interrogate ; extra == 'dev'
Requires-Dist: coverage ; extra == 'dev'
Requires-Dist: mock ; extra == 'dev'
Requires-Dist: pytest (>=4.3.0) ; extra == 'dev'
Requires-Dist: pytest-cov ; extra == 'dev'
Requires-Dist: pytest-mock ; extra == 'dev'
Requires-Dist: dill ; extra == 'dev'
Requires-Dist: bumpversion ; extra == 'dev'
Requires-Dist: wheel ; extra == 'dev'
Provides-Extra: docs
Requires-Dist: sphinx ; extra == 'docs'
Requires-Dist: interrogate ; extra == 'docs'
Provides-Extra: tests
Requires-Dist: coverage ; extra == 'tests'
Requires-Dist: mock ; extra == 'tests'
Requires-Dist: pytest (>=4.3.0) ; extra == 'tests'
Requires-Dist: pytest-cov ; extra == 'tests'
Requires-Dist: pytest-mock ; extra == 'tests'
Requires-Dist: dill ; extra == 'tests'
